spider/__init__.py
spider/css.py
spider/dammit.py
spider/diagnose.py
spider/element.py
spider/formatter.py
spider/builder/__init__.py
spider/builder/_html5lib.py
spider/builder/_htmlparser.py
spider/builder/_lxml.py
spider/tests/__init__.py
spider/tests/test_builder.py
spider/tests/test_builder_registry.py
spider/tests/test_css.py
spider/tests/test_dammit.py
spider/tests/test_docs.py
spider/tests/test_element.py
spider/tests/test_formatter.py
spider/tests/test_fuzz.py
spider/tests/test_html5lib.py
spider/tests/test_htmlparser.py
spider/tests/test_lxml.py
spider/tests/test_navigablestring.py
spider/tests/test_pageelement.py
spider/tests/test_soup.py
spider/tests/test_tag.py
spider/tests/test_tree.py
spider/tests/fuzz/clusterfuzz-testcase-minimized-bs4_fuzzer-4670634698080256.testcase
spider/tests/fuzz/clusterfuzz-testcase-minimized-bs4_fuzzer-4818336571064320.testcase
spider/tests/fuzz/clusterfuzz-testcase-minimized-bs4_fuzzer-4999465949331456.testcase
spider/tests/fuzz/clusterfuzz-testcase-minimized-bs4_fuzzer-5000587759190016.testcase
spider/tests/fuzz/clusterfuzz-testcase-minimized-bs4_fuzzer-5167584867909632.testcase
spider/tests/fuzz/clusterfuzz-testcase-minimized-bs4_fuzzer-5270998950477824.testcase
spider/tests/fuzz/clusterfuzz-testcase-minimized-bs4_fuzzer-5375146639360000.testcase
spider/tests/fuzz/clusterfuzz-testcase-minimized-bs4_fuzzer-5492400320282624.testcase
spider/tests/fuzz/clusterfuzz-testcase-minimized-bs4_fuzzer-5703933063462912.testcase
spider/tests/fuzz/clusterfuzz-testcase-minimized-bs4_fuzzer-5843991618256896.testcase
spider/tests/fuzz/clusterfuzz-testcase-minimized-bs4_fuzzer-5984173902397440.testcase
spider/tests/fuzz/clusterfuzz-testcase-minimized-bs4_fuzzer-6124268085182464.testcase
spider/tests/fuzz/clusterfuzz-testcase-minimized-bs4_fuzzer-6241471367348224.testcase
spider/tests/fuzz/clusterfuzz-testcase-minimized-bs4_fuzzer-6306874195312640.testcase
spider/tests/fuzz/clusterfuzz-testcase-minimized-bs4_fuzzer-6450958476902400.testcase
spider4-4.0.1.dist-info/METADATA
spider4-4.0.1.dist-info/WHEEL
spider4-4.0.1.dist-info/licenses/LICENSE
spider4-4.0.1.dist-info/RECORD
