Metadata-Version: 2.3
Name: spider4
Version: 4.0.1
Summary: Screen-scraping library
Project-URL: Download, https://github.com/shari-ful/spider.git
Project-URL: Homepage, https://github.com/shari-ful/spider.git
Author-email: Shariful Alam <2ashariful@gmail.com>
License: MIT License
License-File: LICENSE
Keywords: HTML,XML,parse,soup
Requires-Python: >=3.6.0
Requires-Dist: soupsieve>1.2
Provides-Extra: cchardet
Requires-Dist: cchardet; extra == 'cchardet'
Provides-Extra: chardet
Requires-Dist: chardet; extra == 'chardet'
Provides-Extra: charset-normalizer
Requires-Dist: charset-normalizer; extra == 'charset-normalizer'
Provides-Extra: html5lib
Requires-Dist: html5lib; extra == 'html5lib'
Provides-Extra: lxml
Requires-Dist: lxml; extra == 'lxml'
